gtirb_client/client.py
gtirb_client/common.py
gtirb_client/version.py
gtirb_client-1.0.1.dist-info/METADATA
gtirb_client-1.0.1.dist-info/WHEEL
gtirb_client-1.0.1.dist-info/entry_points.txt
gtirb_client-1.0.1.dist-info/top_level.txt
gtirb_client-1.0.1.dist-info/RECORD
